{"processTime":"2025-01-14T00:41:54.431Z","trackedLeg":13840,"trackedTime":1994059,"month":{"legs":[{"calId":"23","name":"C.H. Chang","legs":33},{"calId":"32","name":"S.S. Sun","legs":30},{"calId":"7","name":"C.C. Liu","legs":28},{"calId":"25","name":"H.L. Chung","legs":19},{"calId":"34","name":"C.Y. Chen","legs":19}],"time":[{"calId":"23","name":"C.H. Chang","duration":124.1},{"calId":"34","name":"C.Y. Chen","duration":82.4},{"calId":"32","name":"S.S. Sun","duration":64.91666666666667},{"calId":"7","name":"C.C. Liu","duration":57.583333333333336},{"calId":"18","name":"Y.W. Hsu","duration":57.11666666666667}]},"year":{"legs":[{"calId":"23","name":"C.H. Chang","legs":33},{"calId":"32","name":"S.S. Sun","legs":30},{"calId":"7","name":"C.C. Liu","legs":28},{"calId":"25","name":"H.L. Chung","legs":19},{"calId":"34","name":"C.Y. Chen","legs":19}],"time":[{"calId":"23","name":"C.H. Chang","duration":124.1},{"calId":"34","name":"C.Y. Chen","duration":82.4},{"calId":"32","name":"S.S. Sun","duration":64.91666666666667},{"calId":"7","name":"C.C. Liu","duration":57.583333333333336},{"calId":"18","name":"Y.W. Hsu","duration":57.11666666666667}]},"all":{"legs":[{"calId":"7","name":"C.C. Liu","legs":3921},{"calId":"9","name":"Y.C. Su","legs":1405},{"calId":"18","name":"Y.W. Hsu","legs":701},{"calId":"23","name":"C.H. Chang","legs":685},{"calId":"1","name":"C.Y. Liu","legs":647}],"time":[{"calId":"7","name":"C.C. Liu","duration":8712.333333333334},{"calId":"9","name":"Y.C. Su","duration":3373.8333333333335},{"calId":"23","name":"C.H. Chang","duration":1938.2166666666667},{"calId":"18","name":"Y.W. Hsu","duration":1671.2166666666667},{"calId":"1","name":"C.Y. Liu","duration":1485.8}]}}