{"processTime":"2024-10-09T00:42:41.946Z","trackedLeg":12207,"trackedTime":1691744,"month":{"legs":[{"calId":"23","name":"C.H. Chang","legs":77},{"calId":"5","name":"Z.J. Chong","legs":22},{"calId":"11","name":"T.L. Chao","legs":20},{"calId":"7","name":"C.C. Liu","legs":13},{"calId":"32","name":"S.S. Sun","legs":13}],"time":[{"calId":"11","name":"T.L. Chao","duration":195.71666666666667},{"calId":"23","name":"C.H. Chang","duration":135.96666666666667},{"calId":"5","name":"Z.J. Chong","duration":47.85},{"calId":"32","name":"S.S. Sun","duration":33.18333333333333},{"calId":"7","name":"C.C. Liu","duration":24.233333333333334}]},"year":{"legs":[{"calId":"23","name":"C.H. Chang","legs":358},{"calId":"9","name":"Y.C. Su","legs":326},{"calId":"7","name":"C.C. Liu","legs":279},{"calId":"5","name":"Z.J. Chong","legs":226},{"calId":"24","name":"T.W. Hu","legs":215}],"time":[{"calId":"23","name":"C.H. Chang","duration":885.4833333333333},{"calId":"9","name":"Y.C. Su","duration":791.8333333333334},{"calId":"24","name":"T.W. Hu","duration":772.6166666666667},{"calId":"32","name":"S.S. Sun","duration":691.7},{"calId":"7","name":"C.C. Liu","duration":607.6666666666666}]},"all":{"legs":[{"calId":"7","name":"C.C. Liu","legs":3774},{"calId":"9","name":"Y.C. Su","legs":1264},{"calId":"18","name":"Y.W. Hsu","legs":669},{"calId":"1","name":"C.Y. Liu","legs":578},{"calId":"13","name":"J. Juang","legs":512}],"time":[{"calId":"7","name":"C.C. Liu","duration":8387.45},{"calId":"9","name":"Y.C. Su","duration":2964.95},{"calId":"18","name":"Y.W. Hsu","duration":1566.1666666666667},{"calId":"1","name":"C.Y. Liu","duration":1343.1333333333334},{"calId":"24","name":"T.W. Hu","duration":1266.8833333333334}]}}