{"processTime":"2024-12-04T00:48:39.838Z","trackedLeg":13219,"trackedTime":1890374,"month":{"legs":[{"calId":"25","name":"H.L. Chung","legs":6},{"calId":"23","name":"C.H. Chang","legs":5},{"calId":"26","name":"H.W. Lin","legs":4},{"calId":"24","name":"T.W. Hu","legs":2},{"calId":"32","name":"S.S. Sun","legs":2}],"time":[{"calId":"25","name":"H.L. Chung","duration":32.36666666666667},{"calId":"32","name":"S.S. Sun","duration":16.733333333333334},{"calId":"10","name":"Po-Chun Wu","duration":10.533333333333333},{"calId":"23","name":"C.H. Chang","duration":8.433333333333334},{"calId":"26","name":"H.W. Lin","duration":4.166666666666667}]},"year":{"legs":[{"calId":"23","name":"C.H. Chang","legs":602},{"calId":"9","name":"Y.C. Su","legs":467},{"calId":"7","name":"C.C. Liu","legs":356},{"calId":"32","name":"S.S. Sun","legs":288},{"calId":"5","name":"Z.J. Chong","legs":261}],"time":[{"calId":"23","name":"C.H. Chang","duration":1699.3333333333333},{"calId":"9","name":"Y.C. Su","duration":1200.7166666666667},{"calId":"32","name":"S.S. Sun","duration":1140.0166666666667},{"calId":"24","name":"T.W. Hu","duration":895.6666666666666},{"calId":"7","name":"C.C. Liu","duration":803.5333333333333}]},"all":{"legs":[{"calId":"7","name":"C.C. Liu","legs":3851},{"calId":"9","name":"Y.C. Su","legs":1405},{"calId":"18","name":"Y.W. Hsu","legs":684},{"calId":"1","name":"C.Y. Liu","legs":617},{"calId":"23","name":"C.H. Chang","legs":602}],"time":[{"calId":"7","name":"C.C. Liu","duration":8583.316666666668},{"calId":"9","name":"Y.C. Su","duration":3373.8333333333335},{"calId":"23","name":"C.H. Chang","duration":1699.3333333333333},{"calId":"18","name":"Y.W. Hsu","duration":1603.1833333333334},{"calId":"1","name":"C.Y. Liu","duration":1430.8833333333334}]}}