{"processTime":"2024-11-08T00:42:37.832Z","trackedLeg":12747,"trackedTime":1793696,"month":{"legs":[{"calId":"32","name":"S.S. Sun","legs":23},{"calId":"9","name":"Y.C. Su","legs":22},{"calId":"23","name":"C.H. Chang","legs":15},{"calId":"5","name":"Z.J. Chong","legs":12},{"calId":"24","name":"T.W. Hu","legs":8}],"time":[{"calId":"23","name":"C.H. Chang","duration":74.9},{"calId":"9","name":"Y.C. Su","duration":73.9},{"calId":"32","name":"S.S. Sun","duration":53.266666666666666},{"calId":"34","name":"C.Y. Chen","duration":42.28333333333333},{"calId":"5","name":"Z.J. Chong","duration":41.68333333333333}]},"year":{"legs":[{"calId":"23","name":"C.H. Chang","legs":498},{"calId":"9","name":"Y.C. Su","legs":400},{"calId":"7","name":"C.C. Liu","legs":309},{"calId":"5","name":"Z.J. Chong","legs":240},{"calId":"24","name":"T.W. Hu","legs":238}],"time":[{"calId":"23","name":"C.H. Chang","duration":1258.0666666666666},{"calId":"9","name":"Y.C. Su","duration":970.5833333333334},{"calId":"32","name":"S.S. Sun","duration":912.1833333333333},{"calId":"24","name":"T.W. Hu","duration":849.1333333333333},{"calId":"7","name":"C.C. Liu","duration":703.8166666666667}]},"all":{"legs":[{"calId":"7","name":"C.C. Liu","legs":3804},{"calId":"9","name":"Y.C. Su","legs":1338},{"calId":"18","name":"Y.W. Hsu","legs":682},{"calId":"1","name":"C.Y. Liu","legs":598},{"calId":"13","name":"J. Juang","legs":521}],"time":[{"calId":"7","name":"C.C. Liu","duration":8483.6},{"calId":"9","name":"Y.C. Su","duration":3143.7},{"calId":"18","name":"Y.W. Hsu","duration":1601.0833333333333},{"calId":"1","name":"C.Y. Liu","duration":1388.9666666666667},{"calId":"24","name":"T.W. Hu","duration":1343.4}]}}